setup.cfg
setup.py
smartformat/__about__.py
smartformat/__init__.py
smartformat/builtin.py
smartformat/dotnet.py
smartformat/exthook.py
smartformat/local.py
smartformat/smart.py
smartformat/utils.py
smartformat.egg-info/PKG-INFO
smartformat.egg-info/SOURCES.txt
smartformat.egg-info/dependency_links.txt
smartformat.egg-info/not-zip-safe
smartformat.egg-info/requires.txt
smartformat.egg-info/top_level.txt
smartformat/ext/__init__.py